editimg/__init__.py
editimg/imagekit.py
editimg/pngtools.py
editimg-0.1.1.dist-info/licenses/LICENSE
editimg-0.1.1.dist-info/METADATA
editimg-0.1.1.dist-info/WHEEL
editimg-0.1.1.dist-info/top_level.txt
editimg-0.1.1.dist-info/RECORD
