Metadata-Version: 2.4
Name: editimg
Version: 0.1.1
Summary: A collection of simple and easy to use image editing tools.
Home-page: https://github.com/gustavowbu/editimg
Author: Gustavo
Author-email: Gustavo <gustavo.wbu@gmail.com>
License: MIT License
Requires-Python: >=3.9
License-File: LICENSE
Dynamic: author
Dynamic: home-page
Dynamic: license-file
Dynamic: requires-python
